<?xml version="1.0" encoding="UTF-8"?>
<!--
	Changelog:
	v1.0: Created
  v1.1: RS+RH: 8,84 (01.01.2017)
-->
<Salaries version="1.1">
	<Shifttype name="RTW">
		<RA>9.90</RA>
		<RS>8.84</RS>
		<RH>8.84</RH>
	</Shifttype>
	<Shifttype name="KTW">
		<RA>9.90</RA>
		<RS>8.84</RS>
		<RH>8.84</RH>
	</Shifttype>
	<Shifttype name="KIZA">
		<RA>9.90</RA>
		<RS>8.84</RS>
		<RH>8.84</RH>
	</Shifttype>
	<Shifttype name="BREISACH">
		<RA>9.90</RA>
		<RS>8.84</RS>
		<RH>8.84</RH>
	</Shifttype>
	<Shifttype name="EVENT">
		<RA>7.60</RA>
		<RS>6.70</RS>
		<RH>5.90</RH>
	</Shifttype>
	<Shifttype name="KVS">
		<RA>10</RA>
		<RS>10</RS>
		<RH>10</RH>
	</Shifttype>
	<Shifttype name="SC">
		<RA>7.60</RA>
		<RS>6.70</RS>
		<RH>5.90</RH>
	</Shifttype>
	<Shifttype name="CONCERT_HALL">
		<RA>8.50</RA>
		<RS>8.50</RS>
		<RH>8.50</RH>
	</Shifttype>
</Salaries>
